pynixutil/#base32.py#
pynixutil/__init__.py
pynixutil/base32.py
pynixutil/drv.py
pynixutil/py.typed
pynixutil-0.5.0.dist-info/LICENSE
pynixutil-0.5.0.dist-info/WHEEL
pynixutil-0.5.0.dist-info/METADATA
pynixutil-0.5.0.dist-info/RECORD
